{"current":[{"appid":1399440,"name":"Pets VR"},{"appid":1399450,"name":"Hentai Cool Girls - Artbook 18+"},{"appid":1399460,"name":"Museum Of Extravagance"},{"appid":1399480,"name":"California Games"},{"appid":1399530,"name":"Walden Horde"},{"appid":1399540,"name":"A Forgetful Loop"},{"appid":1399560,"name":"Haiki Demo"},{"appid":1399590,"name":"Strike Buster Prototype"},{"appid":1399600,"name":"District 99"},{"appid":1399610,"name":"Lonely Mountains: Downhill ASMR Soundtrack"},{"appid":1399620,"name":"The Caretaker"},{"appid":1399630,"name":"Lactea Volleyball"},{"appid":1399650,"name":"EPEJSODION Dodgeball Defense"},{"appid":1399660,"name":"My Little Prince - a jigsaw puzzle tale"},{"appid":1399670,"name":"Instant Farmer"},{"appid":1399680,"name":"Web Buttons Designer"},{"appid":1399740,"name":"Zball"},{"appid":1399750,"name":"Beholgar"},{"appid":1399760,"name":"Randomlands"},{"appid":1399770,"name":"Space Bar at the End of the Galaxy Adults Only 18+ Patch"},{"appid":1399790,"name":"Lethal League Blaze - Stereo Overdrive Arachnida for Sonata"},{"appid":1399791,"name":"Lethal League Blaze - Gigahertz Visualizer X for Doombox"},{"appid":1399820,"name":"Fantasy Grounds - Aegis of Empires 1: The Book in the Old House"},{"appid":1399830,"name":"Fantasy Grounds - Aegis of Empires 1: The Book in the Old House"},{"appid":1399840,"name":"Neptunia Virtual Stars"},{"appid":1399850,"name":"Squares Rage"},{"appid":1399890,"name":"Starship Renata Demo"},{"appid":1399900,"name":"PolyBeyond"},{"appid":1399910,"name":"Crisis Arcana"},{"appid":1399920,"name":"Hentai Babe Buffy - Expanded Content"},{"appid":1399140,"name":"Boxing Coach"},{"appid":1399150,"name":"VR Time Machine Travelling in ancient civilizations: Mayan Kingdom, Inca Empire, Indians, and Aztecs before conquest A.D.1000"},{"appid":1399170,"name":"Nimbus INFINITY"},{"appid":1399180,"name":"Lone Wolf: World War 2"},{"appid":1399190,"name":"Blood Oath: When The Sword Rises"},{"appid":1399210,"name":"Lumiland"},{"appid":1399220,"name":"Raw April Day"},{"appid":1399230,"name":"Hoovernauts"},{"appid":1399250,"name":"Red Cap Zombie Hunter"},{"appid":1399270,"name":"The Arena Guy"},{"appid":1399280,"name":"The Lost Cube"},{"appid":1399290,"name":"Unpacking Demo"},{"appid":1399300,"name":"SOK PRO"},{"appid":1399310,"name":"Blades of Worlds Demo"},{"appid":1399350,"name":"Beach Volleyball Competition Demo"},{"appid":1399370,"name":"Cute Honey 2"},{"appid":1399380,"name":"NUI"},{"appid":1399400,"name":"VR historical journey to the Buddhist civilizations: VR ancient India and Asia"},{"appid":1399410,"name":"Wreckfest - Racing Heroes Car Pack"},{"appid":1399411,"name":"Wreckfest - Reckless Car Pack"},{"appid":1399412,"name":"Wreckfest - Off-Road Car Pack"},{"appid":1399420,"name":"INMOST Soundtrack"},{"appid":1398660,"name":"CamGirls: Sophie X Rias"},{"appid":1398670,"name":"Dating Life: Emily X Miley"},{"appid":1398680,"name":"Negligee: Girls Night"},{"appid":1398690,"name":"Negligee: Opposites Attract"},{"appid":1398770,"name":"Spiritfarer - Digital Artbook"},{"appid":1398780,"name":"Dungeon Consultant"},{"appid":1398790,"name":"Boobs VR"},{"appid":1398820,"name":"Compost"},{"appid":1398830,"name":"The Goddess of Time and the Ice Princess episode 1"},{"appid":1398860,"name":"Rocket Squad"},{"appid":1398890,"name":"Fast Jump"},{"appid":1398900,"name":"Lost"},{"appid":1398920,"name":"Virtuverse"},{"appid":1398950,"name":"Savage Tower Defense"},{"appid":1398990,"name":"Starship Renata"},{"appid":1399010,"name":"Fantasy Grounds - Black Scrolls Desert Canyons (Map Tile Pack)"},{"appid":1399020,"name":"Krumit's Tale: Varfa the Ranger"},{"appid":1399030,"name":"Wacky Wizarding Dungeon"},{"appid":1399040,"name":"This Is Not Chess"},{"appid":1399050,"name":"Drifters Don't Brake Demo"},{"appid":1399090,"name":"生活模拟器"},{"appid":1399100,"name":"The Unreal Story - The Horror Story"},{"appid":1399111,"name":"The Unreal Story - Outbreak DLC 2"},{"appid":1398200,"name":"ADA: Além d' Aventura"},{"appid":1398210,"name":"Selene ~Apoptosis~"},{"appid":1398220,"name":"IMPAVIDVM"},{"appid":1398240,"name":"Selene ~Apoptosis~ Demo"},{"appid":1398250,"name":"YRek Lost In Portals Demo"},{"appid":1398270,"name":"Furgal's Jetpack"},{"appid":1398290,"name":"Crônicas de Landulph"},{"appid":1398320,"name":"Remalmok"},{"appid":1398350,"name":"DeLight Demo"},{"appid":1398400,"name":"Florida Man: Hurricane Hijinks"},{"appid":1398410,"name":"Reginald's Death Arena"},{"appid":1398420,"name":"One Last Dungeon"},{"appid":1398440,"name":"Transcender"},{"appid":1398460,"name":"Line Leader"},{"appid":1398470,"name":"Pop up Blaster"},{"appid":1398490,"name":"Unreal MAX: Curso básico de Gamedev: Módulo Nº 5"},{"appid":1398500,"name":"MECHBLAZE"},{"appid":1398510,"name":"Galaxy in Peril: Time Trouble"},{"appid":1398520,"name":"Colors of the Cube"},{"appid":1398570,"name":"Last Escape"},{"appid":1398580,"name":"Lawless Lands Community Skin Pack 1 DLC"},{"appid":1398590,"name":"1001 Jigsaw World Tour Asia"},{"appid":1398600,"name":"Fill and Cross World Contest"},{"appid":1398610,"name":"Yag - Antiquity Content"},{"appid":1398620,"name":"Sweet Tooth"}]}