{"current":[{"appid":1150380,"name":"Crossroads Inn Anniversary Edition - Season Pass 2"},{"appid":1150390,"name":"Steel Rain"},{"appid":1150400,"name":"The Ancient Labyrinth"},{"appid":1150410,"name":"Tenderfoot Tactics Demo"},{"appid":1149540,"name":"符文女孩/Rune Girl - Summer Memories/仲夏回忆"},{"appid":1149550,"name":"Utawarerumono: Mask of Deception"},{"appid":1149570,"name":"See"},{"appid":1149580,"name":"Super Korotama"},{"appid":1149590,"name":"Dreamland Solitaire"},{"appid":1149630,"name":"Project: Gemini"},{"appid":1149640,"name":"RimWorld - Royalty"},{"appid":1149650,"name":"Siberian Dawn Mission Pack 2"},{"appid":1149660,"name":"Seek Girl Ⅱ"},{"appid":1149690,"name":"Hexogin"},{"appid":1149700,"name":"Dark Veer"},{"appid":1149710,"name":"Tesla Force"},{"appid":1149720,"name":"Bus Simulator 18 - Setra Bus Pack 1"},{"appid":1149740,"name":"Macrotis: A Mother's Journey Original Soundtrack"},{"appid":1149760,"name":"Project Hospital - Doctor Mode"},{"appid":1149770,"name":"Trapper Simulator"},{"appid":1149780,"name":"Naughty Girl 2 - Original Soundtrack"},{"appid":1149781,"name":"Naughty Girl 2 - Image Pack"},{"appid":1149800,"name":"Xenrai"},{"appid":1149830,"name":"Josie's Tank"},{"appid":1149860,"name":"Arsenal Demon"},{"appid":1149870,"name":"Arsenal Demon Demo"},{"appid":1149900,"name":"Cheer and Track"},{"appid":1149910,"name":"Binky show"},{"appid":1149930,"name":"Tale's Casino Escape"},{"appid":1150010,"name":"Country Clubbing"},{"appid":1150020,"name":"Rhythm Mage VR Demo"},{"appid":1149200,"name":"Spirit Fighters"},{"appid":1149210,"name":"Turtle Rush"},{"appid":1149220,"name":"P.3"},{"appid":1149240,"name":"SUFFER Original Game Soundtrack"},{"appid":1149260,"name":"Ambient DM DLC - (Music) Fantastical"},{"appid":1149261,"name":"Ambient DM DLC - (Music) Halloween"},{"appid":1149270,"name":"IMMURE: Part Two"},{"appid":1149330,"name":"Afterbern"},{"appid":1149340,"name":"Those crazy crows"},{"appid":1149370,"name":"Broken Spell"},{"appid":1149430,"name":"KiKiMiMi2 / 听能力搜查官2"},{"appid":1149440,"name":"Dragon Marked For Death"},{"appid":1149450,"name":"Tree of Life: Oddria!"},{"appid":1149490,"name":"Bokube"},{"appid":1149500,"name":"Arc Vector"},{"appid":1149510,"name":"The Leopard Catgirl in Miaoli"},{"appid":1149520,"name":"foxsoldierp4"},{"appid":1148710,"name":"Miriel Saga"},{"appid":1148740,"name":"Far From Orbit"},{"appid":1148750,"name":"Advisors at the End of the Universe"},{"appid":1148770,"name":"Not An Angels"},{"appid":1148790,"name":"WAR GHOST Demo"},{"appid":1148800,"name":"Trains & Things Editor"},{"appid":1148810,"name":"Tip of the Spear: Task Force Elite"},{"appid":1148820,"name":"Soul room - Dungeons"},{"appid":1148880,"name":"Down In The Dark"},{"appid":1148890,"name":"Protect the campus"},{"appid":1148910,"name":"ShapeWorks"},{"appid":1148920,"name":"Hentai Pix"},{"appid":1148930,"name":"Chuusotsu! 1.5th Graduation: The Moving Castle"},{"appid":1148940,"name":"Hentai Mizugi"},{"appid":1148950,"name":"Hot Takes (Script Code)"},{"appid":1148960,"name":"Kids Cartoon Maker"},{"appid":1148970,"name":"Ashes of Oahu - Brightlocker Mod Pack"},{"appid":1148980,"name":"Occupational Hazards: Episode 1"},{"appid":1149000,"name":"Monster Loves You Too!"},{"appid":1149010,"name":"Warden"},{"appid":1149060,"name":"Vivid! Demo"},{"appid":1149070,"name":"Skyrift"},{"appid":1149080,"name":"Swords and Sandals Spartacus"},{"appid":1149090,"name":"Hospital 9"},{"appid":1149110,"name":"Massive Air Combat - Purchase Privilege DLC"},{"appid":1149120,"name":"Drift 1969"},{"appid":1149130,"name":"Hentai Crazy Girls - Artbook 18+"},{"appid":1149160,"name":"Hentai Crazy Girls - Soundtrack"},{"appid":1149180,"name":"The Last Promise"},{"appid":1149190,"name":"Errant Heart"},{"appid":1148200,"name":"Fado"},{"appid":1148230,"name":"Hexcross"},{"appid":1148240,"name":"Locked & Loaded Demo"},{"appid":1148250,"name":"SoundTriggersVR"},{"appid":1148260,"name":"King of Halloween"},{"appid":1148270,"name":"The Final Battle"},{"appid":1148280,"name":"Super Naughty Maid 2 - Leona's Lewd Talk Voice Drama"},{"appid":1148290,"name":"Thy Kingdom Crumble"},{"appid":1148300,"name":"War Battle Royale Battlegrounds"},{"appid":1148320,"name":"Masteroid"},{"appid":1148330,"name":"Legend of the Sword"},{"appid":1148360,"name":"Alisa Quest"},{"appid":1148390,"name":"Alien Earth"},{"appid":1148400,"name":"Blooming Nightshade"},{"appid":1148410,"name":"Prison Planet"},{"appid":1148420,"name":"Kunoichi Ninja"},{"appid":1148450,"name":"Detective Jackie - Mystic Case"},{"appid":1148460,"name":"Inside The Cubes"},{"appid":1148470,"name":"Killjoy Hunter Yuuko"},{"appid":1148480,"name":"SPACERIFT: Arcanum System"},{"appid":1148500,"name":"PuPaiPo Space Deluxe"},{"appid":1148510,"name":"Pretty Angel"}]}