{"current":[{"appid":1532080,"name":"HeadCount"},{"appid":1532150,"name":"LineArt Jigsaw Puzzle - Erotica 3"},{"appid":1532170,"name":"Veneficium"},{"appid":1532180,"name":"Evo\\Wave"},{"appid":1532190,"name":"Halo: CE Mod Tools"},{"appid":1531320,"name":"Radio Viscera Demo"},{"appid":1531340,"name":"Seasonspree"},{"appid":1531360,"name":"The Wicked Playtest"},{"appid":1531390,"name":"Star Conflict - Pirate weapons Pack"},{"appid":1531400,"name":"Airport Simulator 3: Day & Night - Digital Deluxe Content"},{"appid":1531440,"name":"Mafia Gangster City Background Pack"},{"appid":1531460,"name":"Distorted world"},{"appid":1531472,"name":"Cities: Skylines - Rail Hawk Radio"},{"appid":1531473,"name":"Cities: Skylines - Sunny Breeze Radio"},{"appid":1531480,"name":"Wanba Warriors DLC - Character Pack 3"},{"appid":1531510,"name":"游戏开发的二三事 Demo"},{"appid":1531540,"name":"Distant Worlds 2"},{"appid":1531550,"name":"Megacraft Hentai Battlegrounds"},{"appid":1531570,"name":"Stuffed Demo"},{"appid":1531580,"name":"Dimensions Puzzle"},{"appid":1531590,"name":"Singles' Generation"},{"appid":1531602,"name":"Evil Genius 2: In-Genius Items Pack"},{"appid":1531603,"name":"Evil Genius 2: Rise of the Valkyrie Pack"},{"appid":1531604,"name":"Evil Genius 2: Team Fortress 2 - Pyro Pack"},{"appid":1531610,"name":"Home Designer - Home Sweet Home"},{"appid":1531620,"name":"reIterate()"},{"appid":1531670,"name":"Dino Galaxy Tennis Demo"},{"appid":1557210,"name":"Age of Empires II: Definitive Edition - Dawn of the Dukes"},{"appid":1557230,"name":"Rabbit Riot"},{"appid":1557250,"name":"Rail Route Demo"},{"appid":1557300,"name":"Binger Ninja"},{"appid":1557310,"name":"Dead by Daylight - All-Kill Chapter"},{"appid":1557320,"name":"Mr. Prepper Soundtrack"},{"appid":1557360,"name":"ITERRIA ZONE"},{"appid":1557370,"name":"For The Warp Soundtrack"},{"appid":1557400,"name":"A Museum of Self & Space"},{"appid":1557410,"name":"Black Witchcraft"},{"appid":1557420,"name":"SHIPS AT WAR"},{"appid":1557430,"name":"Midnight is Lost"},{"appid":1557450,"name":"Coloree Demo"},{"appid":1557460,"name":"Slave Fighter X"},{"appid":1557470,"name":"Baby Dragon Rancher"},{"appid":1557490,"name":"Uno - Uno Fenyx’s Quest Theme"},{"appid":1557510,"name":"Myastere -Ruins of Deazniff-"},{"appid":1557540,"name":"Cutie Bear"},{"appid":1557550,"name":"Rogues Adventure"},{"appid":1557560,"name":"Pangman Demo"},{"appid":1557570,"name":"仙劍奇俠傳 音樂精選集"},{"appid":1557590,"name":"Soul at Stake - The Past of Zhai City"},{"appid":1557600,"name":"LEWDAPOCALYPSE Guns&Roses"},{"appid":1557610,"name":"A Knights Adventure Demo"},{"appid":1557670,"name":"Outright"},{"appid":1556729,"name":"Capcom Arcade Stadium：Progear"},{"appid":1556730,"name":"Capcom Arcade Stadium: Display Frames Set 1"},{"appid":1556770,"name":"Mutant Alley: Do The Dinosaur"},{"appid":1556810,"name":"Curse of the Dead Gods - Original Soundtrack"},{"appid":1556830,"name":"Children of Morta: Family Fireside Fables"},{"appid":1556850,"name":"The Lunar Effect"},{"appid":1556860,"name":"Role Player: Full Immersion"},{"appid":1556870,"name":"Golf Club Wasteland"},{"appid":1556900,"name":"Stronghold: Warlords Soundtrack"},{"appid":1556920,"name":"1, 2 BLAME!"},{"appid":1556940,"name":"Aquarist Demo"},{"appid":1556960,"name":"Red Frozen"},{"appid":1556970,"name":"Book of the Old Demo"},{"appid":1556980,"name":"互联网原住民Internet Generation"},{"appid":1557050,"name":"Combat Chess"},{"appid":1557060,"name":"Wonhon: Prologue"},{"appid":1557070,"name":"Cut Them Up"},{"appid":1557100,"name":"Out Of The Shelter"},{"appid":1557110,"name":"Warfield - Multiplayer"},{"appid":1557140,"name":"What Lives Below"},{"appid":1557180,"name":"Ex Natura"},{"appid":1557190,"name":"REFICUL 666"},{"appid":1557200,"name":"My Eyes"},{"appid":1556490,"name":"Retreat To Enen"},{"appid":1556510,"name":"Battlecruisers Soundtrack"},{"appid":1556540,"name":"The Tales of Redbox: An Escape From Desire"},{"appid":1556550,"name":"Chiasm"},{"appid":1556560,"name":"Death Tale Pandora's Box"},{"appid":1556580,"name":"拯救大魔王2:逆流 Falsemen2:Upstream Demo"},{"appid":1556590,"name":"GetsuFumaDen: Undying Moon - Digital Art Book"},{"appid":1556610,"name":"A Conversation With Mister Rabbit"},{"appid":1556620,"name":"Cognition Method: Initiation Soundtrack"},{"appid":1556630,"name":"HuniePop 2: Double Date OST"},{"appid":1556660,"name":"Shell Out Showdown"},{"appid":1556670,"name":"I'm a King"},{"appid":1556680,"name":"OVERSTARS"},{"appid":1556690,"name":"Capcom Arcade Stadium：Ghosts 'n Goblins"},{"appid":1556700,"name":"Capcom Arcade Stadium：VULGUS"},{"appid":1556701,"name":"Capcom Arcade Stadium：PIRATE SHIP HIGEMARU"},{"appid":1556702,"name":"Capcom Arcade Stadium：1942"},{"appid":1556703,"name":"Capcom Arcade Stadium：COMMANDO"},{"appid":1556704,"name":"Capcom Arcade Stadium：SECTION Z"},{"appid":1556705,"name":"Capcom Arcade Stadium：Tatakai no Banka"},{"appid":1556706,"name":"Capcom Arcade Stadium：LEGENDARY WINGS"},{"appid":1556707,"name":"Capcom Arcade Stadium：BIONIC COMMANDO"},{"appid":1556708,"name":"Capcom Arcade Stadium：FORGOTTEN WORLDS"},{"appid":1556709,"name":"Capcom Arcade Stadium：Ghouls 'n Ghosts"},{"appid":1556710,"name":"Capcom Arcade Stadium：STRIDER"}]}