{"current":[{"appid":841370,"name":"NBA 2K19"},{"appid":841440,"name":"ShellBlast"},{"appid":841460,"name":"The Great C"},{"appid":841470,"name":"greenTech+"},{"appid":841500,"name":"Sheep Game"},{"appid":840610,"name":"Fortune-499"},{"appid":840620,"name":"Geometry Boxer"},{"appid":840630,"name":"Fantasy Grounds - Sci-fi Species Vol 1 (Token Pack)"},{"appid":840640,"name":"Ad Movere - Chapter 2"},{"appid":840670,"name":"Good Doggo Premium"},{"appid":840680,"name":"Fantasy Grounds - Scum & Villainy Vol 1 (Token Pack)"},{"appid":840690,"name":"Setup Developer Tool 2018"},{"appid":840700,"name":"Qvabllock"},{"appid":840710,"name":"Trivia Vault: Tennis Trivia"},{"appid":840720,"name":"Sword Art Online: Lost Song"},{"appid":840730,"name":"The Sandbox of God"},{"appid":840750,"name":"Don't Starve Together: Victorian Belongings Chest"},{"appid":840760,"name":"Don't Starve Together: Original Survivors Victorian Chest"},{"appid":840770,"name":"Don't Starve Together: Hallowed Nights Survivors Chest"},{"appid":840790,"name":"The Firlyn Stones"},{"appid":840800,"name":"Outlaws of the Old West"},{"appid":840810,"name":"Data Ball"},{"appid":840830,"name":"Noonie"},{"appid":840840,"name":"Colosso Crystal Skulls"},{"appid":840850,"name":"Kreedz Climbing Development Tools"},{"appid":840860,"name":"I Pay No Rent"},{"appid":840880,"name":"Camped Out!"},{"appid":840890,"name":"Rocket Rush"},{"appid":840910,"name":"Save her, from dreams"},{"appid":840920,"name":"Asimov Laws"},{"appid":840930,"name":"Bing Bong XL"},{"appid":840940,"name":"Spirits of Metropolis"},{"appid":840980,"name":"Exoder"},{"appid":840991,"name":"WAKFU - Brotherhood Pack"},{"appid":841000,"name":"ENDLESS™ Space 2 - Stories"},{"appid":841010,"name":"Jack and Sara: Educational game"},{"appid":841020,"name":"Knockdown the Ball"},{"appid":841030,"name":"Fairy Escape"},{"appid":841080,"name":"Rock 'N Roll Demo"},{"appid":840130,"name":"Battle Royale: Survivors"},{"appid":840140,"name":"武侠乂"},{"appid":840160,"name":"Tokavuh Stream Control"},{"appid":840170,"name":"Delivery man simulator"},{"appid":840180,"name":"On Board 4 PC"},{"appid":840190,"name":"INSECT HAZARD"},{"appid":840210,"name":"Arkham Horror: Mother's Embrace"},{"appid":840220,"name":"Willie Barcena: The Truth Hurts"},{"appid":840230,"name":"Chicken ~Boiled Egg~"},{"appid":840240,"name":"Mosaic: Game of Gods II"},{"appid":840280,"name":"Music Boy 3D Demo"},{"appid":840300,"name":"Supralympic Runners"},{"appid":840310,"name":"SLICE"},{"appid":840370,"name":"Someday You'll Return"},{"appid":840380,"name":"Quible Sphere"},{"appid":840410,"name":"Mushroom Heroes"},{"appid":840430,"name":"Planetary Dustoff"},{"appid":840440,"name":"Good Boy!"},{"appid":840460,"name":"Trailmakers Demo"},{"appid":840490,"name":"Kabounce Beta"},{"appid":840500,"name":"Dictator's dreams"},{"appid":840510,"name":"Furious Drivers"},{"appid":840520,"name":"Cefore OST"},{"appid":840540,"name":"Fantasy Grounds - Monstrous Characters Vol 1 (Token Pack)"},{"appid":840580,"name":"Virtual Foosball"},{"appid":840590,"name":"ANOIX"},{"appid":839660,"name":"Michael Ian Black: Noted Expert"},{"appid":839670,"name":"Alice's Adventures"},{"appid":839680,"name":"The Front of Greed"},{"appid":839690,"name":"Tom Segura: Completely Normal"},{"appid":839710,"name":"Cameron Esposito: Marriage Material"},{"appid":839730,"name":"Planum"},{"appid":839740,"name":"戾谈"},{"appid":839750,"name":"Entre-Deux"},{"appid":839760,"name":"Golden Dungeons - PRO Levels"},{"appid":839810,"name":"Drift 4000"},{"appid":839820,"name":"Match Connect Challenge"},{"appid":839850,"name":"Lenin - The Lion"},{"appid":839860,"name":"Behind The Screen 螢幕判官 - Original Soundtracks"},{"appid":839870,"name":"Wilmot's Warehouse"},{"appid":839890,"name":"Kama Bullet Heritage 2"},{"appid":839910,"name":"Mythgard"},{"appid":839920,"name":"9 Balls"},{"appid":839930,"name":"My Car"},{"appid":839940,"name":"Silverworld"},{"appid":839950,"name":"Silverworld Demo"},{"appid":839970,"name":"Mr Rabbit's Memory"},{"appid":839990,"name":"Fantasy Grounds - Starfinder RPG - Dead Suns AP 5: The Thirteenth Gate (PFRPG)"},{"appid":840020,"name":"Gun Rage"},{"appid":840030,"name":"Patient Seven"},{"appid":840040,"name":"Fantasy Grounds - Moderns Vol 01 (Token Pack)"},{"appid":840050,"name":"ad movere"},{"appid":840060,"name":"Good Doggo"},{"appid":840070,"name":"Koihime Enbu Original Sound Track (for RyoRaiRai)"},{"appid":840090,"name":"Battleground Shooting Training"},{"appid":840100,"name":"Magic Scroll Tactics"},{"appid":840110,"name":"The Beat: A Glam Noir Game"},{"appid":839170,"name":"Paradox of the Cryptomancers"},{"appid":839180,"name":"Nine-Slicer"},{"appid":839190,"name":"看见我~See Me Demo"},{"appid":839210,"name":"The Land of the Seazogs"}]}