{"current":[{"appid":1235480,"name":"Abst Clicker Farm"},{"appid":1235510,"name":"晴空：未来的守望"},{"appid":1235520,"name":"HENTAI DANCE"},{"appid":1235530,"name":"Yag - Cartoon Content"},{"appid":1235570,"name":"Indian Army - Mission POK "},{"appid":1235580,"name":"Greed Demo"},{"appid":1235600,"name":"Weapons of Larth"},{"appid":1235650,"name":"Back To Hell Demo"},{"appid":1235660,"name":"Flatspace (The Official Soundtrack)"},{"appid":1235670,"name":"Flatspace II (The Official Soundtrack)"},{"appid":1235710,"name":"Oddventure"},{"appid":1235720,"name":"The Sims™ 4 Get Famous"},{"appid":1235721,"name":"The Sims™ 4 Cats & Dogs"},{"appid":1235722,"name":"The Sims™ 4 Discover University"},{"appid":1235730,"name":"The Sims™ 4 Island Living"},{"appid":1235731,"name":"The Sims™ 4 City Living"},{"appid":1235732,"name":"The Sims™ 4 Get Together"},{"appid":1235733,"name":"The Sims™ 4 Seasons"},{"appid":1235734,"name":"The Sims™ 4 Get To Work"},{"appid":1235740,"name":"The Sims™ 4 Spa Day"},{"appid":1235741,"name":"The Sims™ 4 Outdoor Retreat"},{"appid":1235742,"name":"The Sims™ 4 StrangerVille"},{"appid":1235744,"name":"The Sims™ 4 Jungle Adventure"},{"appid":1235746,"name":"The Sims™ 4 Realm of Magic"},{"appid":1235747,"name":"The Sims™ 4 Dine Out"},{"appid":1235750,"name":"The Sims™ 4 Fitness Stuff"},{"appid":1235751,"name":"The Sims™ 4 Vintage Glamour Stuff"},{"appid":1235752,"name":"The Sims™ 4 Perfect Patio Stuff"},{"appid":1235753,"name":"The Sims™ 4 My First Pet Stuff"},{"appid":1235754,"name":"The Sims™ 4 Luxury Party Stuff"},{"appid":1235755,"name":"The Sims™ 4 Moschino Stuff"},{"appid":1235756,"name":"The Sims™ 4 Cool Kitchen Stuff"},{"appid":1234920,"name":"TrickShot"},{"appid":1234930,"name":"Reach"},{"appid":1234940,"name":"Astronarch"},{"appid":1234950,"name":"Hunt: Showdown - Soundtrack"},{"appid":1234960,"name":"Greed"},{"appid":1234970,"name":"HOLMGANG: Memories of the Forgotten"},{"appid":1234980,"name":"Live To Win"},{"appid":1235060,"name":"Hentai Honeys Jigsaw - Geisya"},{"appid":1235070,"name":"The Explorer Demo"},{"appid":1235080,"name":"Hentai Honeys Jigsaw - Wife"},{"appid":1235090,"name":"Magical Miri"},{"appid":1235100,"name":"Rolling Hills: Make Sushi, Make Friends"},{"appid":1235120,"name":"Meme Run 2"},{"appid":1235130,"name":"Roboshark Rampage"},{"appid":1235140,"name":"Yakuza: Like a Dragon"},{"appid":1235160,"name":"Boom Stick"},{"appid":1235220,"name":"There a no Armadillos in this game"},{"appid":1235260,"name":"Steam Controller Configs - Secure Desktop"},{"appid":1235320,"name":"Reach Demo"},{"appid":1235330,"name":"White Wings ホワイトウィングス Theme ED Song 逢瀬アキラ.ver"},{"appid":1235340,"name":"Turbo Boom!"},{"appid":1235350,"name":"Weed County"},{"appid":1235360,"name":"Epic Conquest 2"},{"appid":1235370,"name":"Gamedev Beatdown Demo"},{"appid":1235380,"name":"恆夜世界的魔法少女 Demo"},{"appid":1235400,"name":"CATharsis"},{"appid":1235410,"name":"Gamepad Massage - source code"},{"appid":1235440,"name":"長星 Long Star"},{"appid":1234393,"name":"COLOR DEFENSE - ALL MAP UNLOCK"},{"appid":1234400,"name":"Handy Dandy"},{"appid":1234410,"name":"Valiant Gears"},{"appid":1234450,"name":"EDGE OF DAWN"},{"appid":1234460,"name":"Bernadette and the Demon Circus"},{"appid":1234470,"name":"Yuhha: Stolen Treasure Demo"},{"appid":1234490,"name":"Max Gentlemen Sexy Business! Soundtrack"},{"appid":1234510,"name":"Aircraft War: Space Wars"},{"appid":1234520,"name":"The Escaper"},{"appid":1234540,"name":"Bob Wants to Go Home"},{"appid":1234550,"name":"Quest Rooms"},{"appid":1234560,"name":"Rogue Snow: Everwinter"},{"appid":1234570,"name":"Episode 1"},{"appid":1234580,"name":"fullybroKEN - A Unique Post-Apocalyptic RPG"},{"appid":1234590,"name":"Class Kingdom"},{"appid":1234600,"name":"Hollow Remnant"},{"appid":1234610,"name":"BELOW Vol. 3 - Soundtrack"},{"appid":1234620,"name":"Tinker Racers"},{"appid":1234630,"name":"Enemy Gates Stealth War"},{"appid":1234680,"name":"Volatile"},{"appid":1234690,"name":"Gotcha"},{"appid":1234700,"name":"Hornet Virus: Steel Alcimus II"},{"appid":1234710,"name":"Hornet Virus: Steel Alcimus II (Free)"},{"appid":1234740,"name":"Efflorescence of Lust DLC18"},{"appid":1234750,"name":"Penguin's Dogma"},{"appid":1234760,"name":"The shameless squadron Pink woman"},{"appid":1234780,"name":"X-Plane 11 - Add-on: Aerosoft - Airport Chania - Ioannis Daskalogiannis"},{"appid":1234820,"name":"Mistaker"},{"appid":1234830,"name":"Warmth"},{"appid":1234840,"name":"Bone Marrow"},{"appid":1234850,"name":"Synthetic blood: Mind Shift"},{"appid":1234870,"name":"PsyHotel"},{"appid":1234880,"name":"Troll Hunter VR"},{"appid":1234890,"name":"Sokpop S07: labyrinth"},{"appid":1234900,"name":"Sheptun"},{"appid":1234020,"name":"The Epsilon Outcome"},{"appid":1234030,"name":"ゴシックマーダー -運命を変えるアドベンチャー-"},{"appid":1234070,"name":"Wire Flying Maid"},{"appid":1234110,"name":"OH! MOCHI!"},{"appid":1234120,"name":"AeternoBlade"}]}