{"current":[{"appid":838030,"name":"Whitney Cummings: Money Shot"},{"appid":837060,"name":"Soul Smith of the Kingdom Soundtrack"},{"appid":837090,"name":"Chronicles of Mystery - The Tree of Life"},{"appid":837100,"name":"Chronicles of Mystery - The Legend of the Sacred Treasure"},{"appid":837110,"name":"Chronicles of Mystery - Secret of the Lost Kingdom"},{"appid":837140,"name":"JQ: dogs & cats - Soundtrack"},{"appid":837150,"name":"Yuzi Lims: anime runner - Soundtrack"},{"appid":837160,"name":"Realities - glückauf!"},{"appid":837170,"name":"JQ: chemistry - Soundtrack"},{"appid":837180,"name":"Slamoids!"},{"appid":837190,"name":"TANGLEWOOD"},{"appid":837210,"name":"Doodle God: Genesis Secrets"},{"appid":837220,"name":"Doodle Tanks"},{"appid":837240,"name":"Shopkeeper Simulator VR"},{"appid":837260,"name":"Roller Coaster Apocalypse VR"},{"appid":837270,"name":"Tharn"},{"appid":837280,"name":"Lost Borderline"},{"appid":837290,"name":"Blind Mind"},{"appid":837310,"name":"Telophase"},{"appid":837330,"name":"Crimson Shift"},{"appid":837340,"name":"Overchunked - Original Soundtrack"},{"appid":837380,"name":"DeoVR Video Player"},{"appid":837390,"name":"My zero trip"},{"appid":837400,"name":"Fated Kingdom"},{"appid":837430,"name":"Flying Aces - Navy Pilot Simulator"},{"appid":837440,"name":"MineSweep"},{"appid":837450,"name":"Heaven Will Be Mine Soundtrack"},{"appid":837460,"name":"Batbarian: Testament of the Primordials"},{"appid":837470,"name":"Untitled Goose Game"},{"appid":837500,"name":"Leder Panzer"},{"appid":837530,"name":"Dark Ghost RPG"},{"appid":837550,"name":"Bouncy Butter Ball"},{"appid":836700,"name":"Doctor Flow"},{"appid":836710,"name":"Panzer Hearts Demo"},{"appid":836730,"name":"Panzer Hearts OST and Artbook"},{"appid":836750,"name":"Rainbow Six Siege - Pro League Lesion Set"},{"appid":836760,"name":"Sorcery Saga: Curse of the Great Curry God"},{"appid":836770,"name":"Art of Murder - Cards of Destiny"},{"appid":836781,"name":"Rainbow Six Siege - Pro League Echo Set"},{"appid":836783,"name":"Rainbow Six Siege - Pro League Capitao Set"},{"appid":836785,"name":"Rainbow Six Siege - Pro League Kapkan Set"},{"appid":836790,"name":"Dr. Pills"},{"appid":836810,"name":"Sword Art Online: Fatal Bullet - Ambush of the Imposters "},{"appid":836811,"name":"Sword Art Online: Fatal Bullet - Betrayal of Comrades"},{"appid":836812,"name":"SWORD ART ONLINE: FATAL BULLET - Collapse of Balance"},{"appid":836820,"name":"Pinball FX3 - Star Wars™ Pinball: The Last Jedi"},{"appid":836830,"name":"XXZ: Rush Trial"},{"appid":836840,"name":"Simon the Sorcerer - Legacy Edition (English)"},{"appid":836841,"name":"Simon the Sorcerer - Legacy Edition (German)"},{"appid":836842,"name":"Simon the Sorcerer - Legacy Edition (French)"},{"appid":836843,"name":"Simon the Sorcerer - Legacy Edition (Spanish)"},{"appid":836844,"name":"Simon the Sorcerer - Legacy Edition (Italian)"},{"appid":836845,"name":"Simon the Sorcerer - Legacy Edition (Russian)"},{"appid":836846,"name":"Simon the Sorcerer - Legacy Edition (Hebrew)"},{"appid":836850,"name":"Tiny Tanks"},{"appid":836860,"name":"Art of Murder - The Secret Files"},{"appid":836870,"name":"Art of Murder - Deadly Secrets"},{"appid":836880,"name":"The Berlin Wall"},{"appid":836890,"name":"Kingdom Come: Deliverance - HD Texture Pack"},{"appid":836900,"name":"Kingdom Come: Deliverance - HD Sound Pack"},{"appid":836910,"name":"Kingdom Come: Deliverance - HD Voice Pack - English"},{"appid":836920,"name":"Kingdom Come: Deliverance - HD Voice Pack - German"},{"appid":836930,"name":"Kingdom Come: Deliverance - HD Voice Pack - French"},{"appid":836940,"name":"【SCP】器関ノ彷徨 -The will of a single Tale-【DEMOver.】"},{"appid":837040,"name":"Redneck Kentucky and the Next Generation Chickens"},{"appid":836230,"name":"Heavy Blade"},{"appid":836260,"name":"Call of Bitcoin"},{"appid":836270,"name":"Jerome Bixby's Man from Earth"},{"appid":836280,"name":"Dynamite Bunny"},{"appid":836290,"name":"Achievement Lurker: Ballad of the Shimapan Warrior - King of Panties"},{"appid":836300,"name":"Humble Pie"},{"appid":836310,"name":"Gun Done: WHO IS AWESOME"},{"appid":836320,"name":"Simon the Sorcerer 2 - Legacy Edition (German)"},{"appid":836321,"name":"Simon the Sorcerer 2 - Legacy Edition (French)"},{"appid":836330,"name":"The God"},{"appid":836340,"name":"Qinoto"},{"appid":836350,"name":"Heartbreak High: A Break-Up Simulator"},{"appid":836370,"name":"Inexplicable Geeks, Outfit Pack: Twitch Con 2018"},{"appid":836380,"name":"Paper Shakespeare, Outfit Pack: Shark Week"},{"appid":836400,"name":"Basketball Hero VR"},{"appid":836420,"name":"Beginner'sGame"},{"appid":836440,"name":"MonsterxMan: Inheritance To Lust"},{"appid":836450,"name":"Heaven Will Be Mine"},{"appid":836460,"name":"Etherian"},{"appid":836470,"name":"Mage Fort"},{"appid":836480,"name":"恋爱模拟器 Love Simulation"},{"appid":836490,"name":"月夜下的紅茶杯 ~ Blacktea With Moon"},{"appid":836510,"name":"Paper Shakespeare: The Legend of Rainbow Hollow: Extra Time for Professional Gamers Only"},{"appid":836520,"name":"Paper Shakespeare: The Legend of Rainbow Hollow: Official Soundtrack"},{"appid":836530,"name":"Paper Shakespeare: The Legend of Rainbow Hollow: Hint Button Helper for Professional Gamers Only"},{"appid":836540,"name":"Viking Brothers 2"},{"appid":836550,"name":"Viking Brothers 3"},{"appid":836560,"name":"Viking Brothers 4"},{"appid":836570,"name":"Inexplicable Geeks: Mandated Company Wide Reboot"},{"appid":836580,"name":"Dead GroundZ"},{"appid":836590,"name":"STAY COOL, KOBAYASHI-SAN!: A RIVER CITY RANSOM STORY"},{"appid":836600,"name":"Alternate Jake Hunter: DAEDALUS The Awakening of Golden Jazz"},{"appid":836610,"name":"Jigsaw 360"},{"appid":836630,"name":"Black Desert - Limited Package"},{"appid":836631,"name":"Black Desert - Prime Package"}]}