{"current":[{"appid":1194100,"name":"Musical Aim Trainer"},{"appid":1194130,"name":"Paradise Away"},{"appid":1194140,"name":"Blind Justice"},{"appid":1194160,"name":"One-Eyed Lee and the Dinner Party"},{"appid":1194170,"name":"Foe Frenzy"},{"appid":1194190,"name":"The Ugly Christmas Sweater Game"},{"appid":1194200,"name":"Gem Jam"},{"appid":1194220,"name":"Zombie Tag Royale"},{"appid":1194230,"name":"Sword story"},{"appid":1194250,"name":"Screaming Chicken: Ultimate Showdown"},{"appid":1194270,"name":"Trainz 2019 DLC - Canadian Rocky Mountains Ottertail to Castle Jct"},{"appid":1194330,"name":"Drone Combat"},{"appid":1194360,"name":"TribeXR - Snow Decks Skin"},{"appid":1194361,"name":"TribeXR - Guerrilla Decks Skin"},{"appid":1194380,"name":"Volleyball Fever Flat"},{"appid":1194390,"name":"The Land of Crows"},{"appid":1194430,"name":"Trainz 2019 DLC - Canadian Rocky Mountains Viktor Lake to Ross Peak and Glacier"},{"appid":1194440,"name":"Zaccaria Pinball - Red Show Deluxe Table"},{"appid":1194470,"name":"Overdungeon - Mr.Almighty (Card Pack)"},{"appid":1194480,"name":"Cursed Gem"},{"appid":1194490,"name":"Dethcube"},{"appid":1194500,"name":"Star Conflict: Ze'Ta. Deluxe Version"},{"appid":1194520,"name":"Terra Incognita"},{"appid":1194540,"name":"Hero Siege - Vampire Hunter (Skin)"},{"appid":1193690,"name":"爱丽娅的明日盛典！Original Soundtrack"},{"appid":1193730,"name":"Piece Of Mind"},{"appid":1193750,"name":"StrikeForce Kitty - Original Soundtrack"},{"appid":1193760,"name":"WarriOrb: Prologue"},{"appid":1193780,"name":"Tower Climb"},{"appid":1193790,"name":"UNHERD"},{"appid":1193830,"name":"Jeremiah"},{"appid":1193840,"name":"Crossout - Polymorph pack"},{"appid":1193860,"name":"New York Mysteries: The Outbreak Demo"},{"appid":1193870,"name":"Fantasy General II: Empire Aflame"},{"appid":1193871,"name":"Fantasy General II: Onslaught"},{"appid":1193890,"name":"FURRY GIRL PUZZLE - LUXE PACK💝"},{"appid":1193900,"name":"Island Marauder"},{"appid":1193930,"name":"Ping Pong Space"},{"appid":1193950,"name":"Dashbot Ninja"},{"appid":1193990,"name":"Trapped"},{"appid":1194000,"name":"NITE Team 4: Withering Dusk"},{"appid":1194010,"name":"Outward - The Soroboreans"},{"appid":1194020,"name":"Loop-Loop DX: Official Soundtrack"},{"appid":1194021,"name":"Loop-Loop DX: Supporter Pack"},{"appid":1194050,"name":"Orange Cast"},{"appid":1194060,"name":"Eternal Hope Demo"},{"appid":1193220,"name":"Tale's Casino Escape Demo"},{"appid":1193240,"name":"GearCity Demo"},{"appid":1193280,"name":"Reverse Fantasy Legend 2 逆袭幻想传2"},{"appid":1193290,"name":"Wonder Cat"},{"appid":1193300,"name":"Axe Cop"},{"appid":1193320,"name":"Nyanco Channel - Dream Pack"},{"appid":1193330,"name":"Together - A Wish No One Remembers"},{"appid":1193340,"name":"Zelter"},{"appid":1193350,"name":"生物知识格斗大赛"},{"appid":1193360,"name":"Hospital 9 - Puzzles"},{"appid":1193370,"name":"Rise of the Dragons"},{"appid":1193380,"name":"The Visitors"},{"appid":1193390,"name":"Wurroom - Support the Developer!"},{"appid":1193400,"name":"Degraman: Act I. Vincent & Cassel Demo"},{"appid":1193410,"name":"Hentai Picross - Nudity"},{"appid":1193420,"name":"The Dis-United States Of America"},{"appid":1193430,"name":"Vapormaze"},{"appid":1193440,"name":"Pax Romana: Romulus - Venit Hiems"},{"appid":1193450,"name":"Stripper Anya: Christmas Special"},{"appid":1193460,"name":"Bunny Sudoku"},{"appid":1193470,"name":"Drop Cat"},{"appid":1193480,"name":"Justin Wack and the Big Time Hack Demo"},{"appid":1193490,"name":"A Crooked Heart"},{"appid":1193510,"name":"Antarctic Heritage Trust"},{"appid":1193520,"name":"Space Climber"},{"appid":1193530,"name":"Black Smith"},{"appid":1193550,"name":"Ruthless Conquest"},{"appid":1193560,"name":"Roast Party"},{"appid":1193570,"name":"Drawkanoid: Review Breaker"},{"appid":1193600,"name":"Meandering Fiend"},{"appid":1193610,"name":"LET IT DIE -(Special)10 Death Metals- 013"},{"appid":1193611,"name":"LET IT DIE -(Special)50 Death Metals- 010"},{"appid":1193612,"name":"LET IT DIE -(Special)Express Pass- 004"},{"appid":1193613,"name":"LET IT DIE -(Year 3 Anniversary) 300 Death Metals-"},{"appid":1193620,"name":"The Aftermath: Unnatural Selection"},{"appid":1193630,"name":"锋芒录"},{"appid":1193640,"name":"Trainz Route: Beavermouth to Ottertail"},{"appid":1193660,"name":"Jack-O-Lantern Covers of Darkness"},{"appid":1193680,"name":"Alien Invasion 3D part 2"},{"appid":1192730,"name":"ADULT SHERIFF"},{"appid":1192740,"name":"Woman's body: For adults 2"},{"appid":1192770,"name":"Fantasy Grounds - Dungeon Crawl Classics Horror #5: Creep, Skrag, Creep! (DCC)"},{"appid":1192790,"name":"Turkey, Please!"},{"appid":1192810,"name":"RV"},{"appid":1192820,"name":"Miscreated - Canyonlands"},{"appid":1192840,"name":"The Shenanigans of Cherry and Trix"},{"appid":1192860,"name":"Winter Snow | 冬雪"},{"appid":1192880,"name":"Nostalgiarian"},{"appid":1192890,"name":"Shoot Them"},{"appid":1192900,"name":"Iron Rebellion"},{"appid":1192910,"name":"食用系少女：美食內戰 Food Girls：Civil War"},{"appid":1192920,"name":"Octofurry - 18+ Content"},{"appid":1192940,"name":"Monkey GO Happy"},{"appid":1192950,"name":"砌墙 Qi Qiang"}]}