{"current":[{"appid":1573890,"name":"The Tower Between Us"},{"appid":1573918,"name":"The Legend of Heroes: Trails of Cold Steel IV - Self-Assertion Panels Vol. 2"},{"appid":1573920,"name":"Female pack 01 for Clip maker"},{"appid":1573930,"name":"Porn stars for Clip maker"},{"appid":1573940,"name":"God of the Arena Dungeon - Fat Rat Edition"},{"appid":1573950,"name":"Commoners"},{"appid":1573190,"name":"Unite"},{"appid":1573210,"name":"Desktop AI - Lily"},{"appid":1573220,"name":"Low-Key: A Dope Game"},{"appid":1573230,"name":"Magicians Legacy: Prologue - Artbook"},{"appid":1573250,"name":"Allura: The Three Realms"},{"appid":1573260,"name":"Injoku Furin - Deluxe Pack"},{"appid":1573280,"name":"WW2 Rebuilder"},{"appid":1573330,"name":"Unreal Sandbox"},{"appid":1573340,"name":"USSR CHAN: Hentai Puzzle Game Demo"},{"appid":1573350,"name":"Coastline Flight Simulator"},{"appid":1573380,"name":"Lust from Beyond - Goodies Pack"},{"appid":1573390,"name":"Lila’s Sky Ark"},{"appid":1573400,"name":"葬花 Demo"},{"appid":1573410,"name":"Malone In Nightmares"},{"appid":1573420,"name":"Photo-Life - Rina's Journey"},{"appid":1573430,"name":"Carnival and Girls"},{"appid":1573460,"name":"Car Scrapyard Simulator"},{"appid":1573490,"name":"Magic Twins Soundtrack"},{"appid":1573500,"name":"Red Measures"},{"appid":1573510,"name":"Super Dream Dasher DEMO"},{"appid":1573520,"name":"Flow Gear Racing Demo"},{"appid":1573530,"name":"Prison 69"},{"appid":1573540,"name":"Space Amoeba - StarShip Constructor"},{"appid":1573580,"name":"CATch the Stars: Japan"},{"appid":1573590,"name":"Colonize"},{"appid":1573600,"name":"ECHOLOCAUTION Original Soundtrack"},{"appid":1573660,"name":"Vinyl Reality Demo"},{"appid":1573670,"name":"The Fabled Woods - Notebook"},{"appid":1573680,"name":"The Fabled Woods Soundtrack"},{"appid":1572790,"name":"Gustavo : Kingdom Rebirth"},{"appid":1572800,"name":"Neon Snake"},{"appid":1572810,"name":"МЕМОЛОГИЯ"},{"appid":1572820,"name":"Lux mina Soundtrack"},{"appid":1572830,"name":"Before the battery´s over"},{"appid":1572870,"name":"Fantasy Grounds - Pathfinder RPG - Shattered Star AP 1: Shards of Sin"},{"appid":1572880,"name":"Gentle Club"},{"appid":1572890,"name":"Girls on puzzle 4 - Wallpapers"},{"appid":1572891,"name":"Girls on puzzle 4 - Wallpapers 2"},{"appid":1572892,"name":"Girls on puzzle 4 - Wallpapers 3"},{"appid":1572893,"name":"Girls on puzzle 4 - Wallpapers 4"},{"appid":1572894,"name":"Girls on puzzle 4 - Wallpapers +18"},{"appid":1572910,"name":"Bouncy Cloud"},{"appid":1572930,"name":"Void's Blight"},{"appid":1572950,"name":"CAT Interstellar: Episode II"},{"appid":1572960,"name":"Train 113"},{"appid":1572970,"name":"Liberation Mutagenix"},{"appid":1572990,"name":"Twilight Town: A Cyberpunk Day In Life"},{"appid":1573000,"name":"Causality Soundtrack"},{"appid":1573010,"name":"bHapticsPlayer"},{"appid":1573020,"name":"MultiMind Challengers Demo"},{"appid":1573050,"name":"Tree of Savior - Cherry Blossom in March 2021 OST Collection "},{"appid":1573060,"name":"ネジ込みシミュレーターVol1 -おかっぱ巨乳ちゃんを簡単マウス操作で極太ディルドーにずぽずぽさせる疑似オナホアプリ-【拡張・オナホ化・石化・時間停止】"},{"appid":1573070,"name":"Endless Furry Blackjack"},{"appid":1573080,"name":"Recoiled"},{"appid":1573100,"name":"Subterrain : Mines of Titan"},{"appid":1573130,"name":"VR Chinese Garden Tour (HD): Flying as a dragonfly"},{"appid":1573140,"name":"ROUGH KUTS: Attack of the Giant Leeches"},{"appid":1573141,"name":"ROUGH KUTS: Dementia 13"},{"appid":1573160,"name":"JustDefense"},{"appid":1573170,"name":"Games and Girls"},{"appid":1573180,"name":"Injoku Furin"},{"appid":1572050,"name":"Crash Race"},{"appid":1572080,"name":"HomeWind"},{"appid":1572100,"name":"Girls on puzzle 4"},{"appid":1572120,"name":"Unblock Me Car"},{"appid":1572160,"name":"Kazakh 'Jack Soundtrack"},{"appid":1572180,"name":"Lionfish Reef Patrol"},{"appid":1572190,"name":"Hyposphere Z"},{"appid":1572200,"name":"Crafty Demo"},{"appid":1572220,"name":"Guns and Grapples"},{"appid":1572230,"name":"Nami"},{"appid":1572250,"name":"Keridwen Demo"},{"appid":1572260,"name":"Wild Ice"},{"appid":1572270,"name":"F.I.S.H."},{"appid":1572280,"name":"Isolationist Nightclub Simulator Soundtrack"},{"appid":1572320,"name":"Malfunction II"},{"appid":1572330,"name":"Hero of the Demon"},{"appid":1572340,"name":"Ark of Artemis"},{"appid":1572380,"name":"Future Fortune"},{"appid":1572400,"name":"Elemental Angel"},{"appid":1572410,"name":"Super Woden GP Demo"},{"appid":1572420,"name":"Leenie Boog"},{"appid":1572430,"name":"Elemental Angel DLC-1"},{"appid":1572431,"name":"Elemental Angel DLC-2"},{"appid":1572432,"name":"Elemental Angel DLC-3"},{"appid":1572433,"name":"Elemental Angel DLC-4"},{"appid":1572450,"name":"Femboy Besties"},{"appid":1572470,"name":"Höll Space 5D6"},{"appid":1572480,"name":"Through The Fragmentation Demo"},{"appid":1572500,"name":"Worms Rumble - Spaceworm and Alien Double Pack"},{"appid":1571590,"name":"Steel Division 2 - Nemesis #4 - Storming Toulon"},{"appid":1571600,"name":"Dark Romance: Sleepy Hollow Collector's Edition"},{"appid":1571630,"name":"Legend of Zuri - Art Collection"},{"appid":1571640,"name":"stardust"}]}