{"current":[{"appid":1399030,"name":"Wacky Wizarding Dungeon"},{"appid":1399040,"name":"This Is Not Chess"},{"appid":1399050,"name":"Drifters Don't Brake Demo"},{"appid":1399090,"name":"生活模拟器"},{"appid":1399100,"name":"The Unreal Story - The Horror Story"},{"appid":1399111,"name":"The Unreal Story - Outbreak DLC 2"},{"appid":1398200,"name":"ADA: Além d' Aventura"},{"appid":1398210,"name":"Selene ~Apoptosis~"},{"appid":1398220,"name":"IMPAVIDVM"},{"appid":1398240,"name":"Selene ~Apoptosis~ Demo"},{"appid":1398250,"name":"YRek Lost In Portals Demo"},{"appid":1398270,"name":"Furgal's Jetpack"},{"appid":1398290,"name":"Crônicas de Landulph"},{"appid":1398320,"name":"Remalmok"},{"appid":1398350,"name":"DeLight Demo"},{"appid":1398400,"name":"Florida Man: Hurricane Hijinks"},{"appid":1398410,"name":"Reginald's Death Arena"},{"appid":1398420,"name":"One Last Dungeon"},{"appid":1398440,"name":"Transcender"},{"appid":1398460,"name":"Line Leader"},{"appid":1398470,"name":"Pop up Blaster"},{"appid":1398490,"name":"Unreal MAX: Curso básico de Gamedev: Módulo Nº 5"},{"appid":1398500,"name":"MECHBLAZE"},{"appid":1398510,"name":"Galaxy in Peril: Time Trouble"},{"appid":1398520,"name":"Colors of the Cube"},{"appid":1398570,"name":"Last Escape"},{"appid":1398580,"name":"Lawless Lands Community Skin Pack 1 DLC"},{"appid":1398590,"name":"1001 Jigsaw World Tour Asia"},{"appid":1398600,"name":"Fill and Cross World Contest"},{"appid":1398610,"name":"Yag - Antiquity Content"},{"appid":1398620,"name":"Sweet Tooth"},{"appid":1398630,"name":"无限次元"},{"appid":1398640,"name":"White Hell Demo"},{"appid":1397700,"name":"Taivas Demo"},{"appid":1397710,"name":"Operation TP"},{"appid":1397720,"name":"Red Sector"},{"appid":1397760,"name":"Pulse Jumper"},{"appid":1397780,"name":"Pulse Jumper Demo"},{"appid":1397790,"name":"Samurai Gunn 2"},{"appid":1397800,"name":"Please Wake Up"},{"appid":1397810,"name":"Ducktopia"},{"appid":1397820,"name":"Sky Mirror · Strolling"},{"appid":1397840,"name":"Cult of Dawn"},{"appid":1397850,"name":"Circle Tank"},{"appid":1397880,"name":"The Weald"},{"appid":1397940,"name":"Prototype Zordi Mi Lé"},{"appid":1397950,"name":"绯红之都"},{"appid":1397960,"name":"One Night on Halloween"},{"appid":1397980,"name":"THE NORMAL THING"},{"appid":1397990,"name":"The Tower Of TigerQiuQiu Super Tigerio"},{"appid":1398010,"name":"Battle Ready"},{"appid":1398030,"name":"Eternal dark winter"},{"appid":1398050,"name":"ISEKAI QUEST : Artbook + Digital Album"},{"appid":1398060,"name":"ISEKAI QUEST : True Vision"},{"appid":1398080,"name":"Seaside Cafe Story"},{"appid":1398090,"name":"BOY BEATS WORLD Demo"},{"appid":1398100,"name":"Orwell's Animal Farm"},{"appid":1398110,"name":"Space Pirate King"},{"appid":1398120,"name":"The Hardest Thing Ever"},{"appid":1398130,"name":"Head Bumper: Editcraft"},{"appid":1398150,"name":"`asdf` Playtest (Deleted)"},{"appid":1398160,"name":"Eye of the Temple Demo"},{"appid":1398170,"name":"Mourning Inc."},{"appid":1398180,"name":"Porcini"},{"appid":1397230,"name":"VR Time Machine Travelling in history: Visit ancient Egypt, Babylon and Greece in B.C. 400"},{"appid":1397240,"name":"MEGAJUMP"},{"appid":1397250,"name":"My Train Arrives - City pack"},{"appid":1397270,"name":"Knight Arena"},{"appid":1397280,"name":"Slime Pandemic TD"},{"appid":1397290,"name":"Comet 64"},{"appid":1397300,"name":"Kyma Maker's Island"},{"appid":1397310,"name":"About Love, Hate And The Other Ones 2 Demo"},{"appid":1397320,"name":"Craft In Abyss Soundtrack"},{"appid":1397340,"name":"Tennis World Tour 2 - Sofia Kenin & Karolina Pliskova"},{"appid":1397350,"name":"好久不见 - Long Time No See"},{"appid":1397360,"name":"Shattered Runes"},{"appid":1397370,"name":"RuneScape: Original Soundtrack Classics"},{"appid":1397380,"name":"Hunt: Showdown - Ronin"},{"appid":1397381,"name":"Hunt: Showdown - The Trick Shooter"},{"appid":1397390,"name":"The Break-In"},{"appid":1397400,"name":"Portals World Demo"},{"appid":1397410,"name":"烈焰天下"},{"appid":1397420,"name":"Aloof Demo"},{"appid":1397430,"name":"Itorah Demo"},{"appid":1397470,"name":"Tsuro - The Game of The Path"},{"appid":1397480,"name":"Tennis World Tour 2 Annual Pass"},{"appid":1397490,"name":"Total Tank Simulator – Italy DLC"},{"appid":1397530,"name":"Monochro"},{"appid":1397540,"name":"On Pixels: A lights out game"},{"appid":1397600,"name":"Fantasy Grounds - Does Love Forgive?"},{"appid":1397610,"name":"Unrailed! Demo"},{"appid":1397620,"name":"Flat Earth Simulator"},{"appid":1397650,"name":"Jetborne Racing"},{"appid":1397670,"name":"Aeon Drive Demo"},{"appid":1397680,"name":"Glory Hold"},{"appid":1397690,"name":"Riot At World"},{"appid":1396750,"name":"Fantasy Grounds - Tomb of the Kirin-Born Prince"},{"appid":1396780,"name":"Fantasy Grounds - Fantasy Grounds Unity Ultimate License Upgrade"},{"appid":1396800,"name":"Fantasy Grounds - Black Scrolls Pirate and Ghost Ship (Map Tile Pack)"},{"appid":1396820,"name":"Fantasy Grounds - Rise of the Drow: Collector's Edition"}]}