{"current":[{"appid":639370,"name":"Professor Teaches Accounting Fundamentals"},{"appid":639390,"name":"Naruto Spin-Off: Rock Lee & His Ninja Pals: My First Five-Star Sushi! / Friendship, Effort, and Victory!"},{"appid":639391,"name":"Naruto Spin-Off: Rock Lee & His Ninja Pals: Hunting for Matsutake Mushrooms! / Lee and Neji Part Ways!"},{"appid":639392,"name":"Naruto Spin-Off: Rock Lee & His Ninja Pals: We're Here to Welcome Gaara! / the Ultimate Autumn Diet!"},{"appid":639393,"name":"Naruto Spin-Off: Rock Lee & His Ninja Pals: Autumn Shinobi Safety Lessons! / Deidara's Art Is Always a Blast!"},{"appid":639394,"name":"Naruto Spin-Off: Rock Lee & His Ninja Pals: Nothing Beats Mixed Bathing! / October 27th WAS Orochimaru's Birthday"},{"appid":639395,"name":"Naruto Spin-Off: Rock Lee & His Ninja Pals: Sakura's My Nurse! / One Vote for Rock Lee!"},{"appid":639396,"name":"Naruto Spin-Off: Rock Lee & His Ninja Pals: Might Guy: A Story of Love and Hair / Substitute Narrator!"},{"appid":639397,"name":"Naruto Spin-Off: Rock Lee & His Ninja Pals: Save Ichiraku Ramen! / Vacations Are for Training!"},{"appid":639398,"name":"Naruto Spin-Off: Rock Lee & His Ninja Pals: Caring for Animals Is Hard Work / Shout It Out! at Naruto!"},{"appid":639399,"name":"Naruto Spin-Off: Rock Lee & His Ninja Pals: Tenten vs. Temari! / Orochimaru's Search for Love!"},{"appid":639400,"name":"Naruto Spin-Off: Rock Lee & His Ninja Pals: Guy-Sensei Is the New Hokage! / IQ: 200. Status: Troublesome."},{"appid":639401,"name":"Naruto Spin-Off: Rock Lee & His Ninja Pals: Infiltrate Akatsuki's Hideout! / Cleanup Is a Chance to Wash Away the Past!"},{"appid":639402,"name":"Naruto Spin-Off: Rock Lee & His Ninja Pals: Christmas Is the Last Chance for Love! / Orochimaru's Search for Love!"},{"appid":639410,"name":"Naruto Spin-Off: Rock Lee & His Ninja Pals: A New Year's Escape Clause! / Naruto Under Surveillance!"},{"appid":639411,"name":"Naruto Spin-Off: Rock Lee & His Ninja Pals: An Endless Nightmare / a Robot from the Future!"},{"appid":639412,"name":"Naruto Spin-Off: Rock Lee & His Ninja Pals: Shino Loves Insects / Tenten Fights a Maiden's Battle!"},{"appid":639413,"name":"Naruto Spin-Off: Rock Lee & His Ninja Pals: 17 Nights of Staying Out of Sight / Cleaning the Bathroom Cleanses the Soul"},{"appid":639414,"name":"Naruto Spin-Off: Rock Lee & His Ninja Pals: The Staff Will Eat the Beans Afterwards! / The Raikage Is Under Attack!"},{"appid":639415,"name":"Naruto Spin-Off: Rock Lee & His Ninja Pals: A Fiery Snow Sculpting Contest! / the Battlefield Called Valentine's Day!"},{"appid":639416,"name":"Naruto Spin-Off: Rock Lee & His Ninja Pals: The Legendary Sannin, Jiraiya! / Infiltrate the Women's Bath!"},{"appid":639417,"name":"Naruto Spin-Off: Rock Lee & His Ninja Pals: Dogs Need Dog Friends/It's HIM!"},{"appid":639418,"name":"Naruto Spin-Off: Rock Lee & His Ninja Pals: Yamato Gets a Mission!/Leaf Village of the Dead!"},{"appid":639419,"name":"Naruto Spin-Off: Rock Lee & His Ninja Pals: The Alliance to Destroy White Day! / Clean up the Dolls!"},{"appid":639420,"name":"Naruto Spin-Off: Rock Lee & His Ninja Pals: Babysitting Guy Sensei! / Lady Tsunade's Marriage Interview!"},{"appid":639421,"name":"Naruto Spin-Off: Rock Lee & His Ninja Pals: The Final Battle / Our Final Mission Is S-Ranked!"},{"appid":639430,"name":"H1Z1: King of the Kill - USA Hoodie"},{"appid":639434,"name":"H1Z1: King of the Kill - South Korea Hoodie"},{"appid":639114,"name":"Party Down: Sin Say Shun Awards After Party"},{"appid":639115,"name":"Party Down: Taylor Stiltskin Sweet Sixteen"},{"appid":639116,"name":"Party Down: Brandix Corporate Retreat"},{"appid":639117,"name":"Party Down: Celebrate Ricky Sargulesh"},{"appid":639118,"name":"Party Down: James Rolf High School Twentieth Reunion"},{"appid":639119,"name":"Party Down: Stennheiser-Pong Wedding Reception"},{"appid":639120,"name":"Party Down: Jackal Onassis Backstage Party"},{"appid":639121,"name":"Party Down: Precious Lights Pre-School Auction"},{"appid":639122,"name":"Party Down: Nick Dicinto's Orgy Night"},{"appid":639123,"name":"Party Down: James Ellison Funeral"},{"appid":639124,"name":"Party Down: Steve Guttenberg's Birthday"},{"appid":639125,"name":"Party Down: \"Not On Your Wife\" Opening Night"},{"appid":639126,"name":"Party Down: Party Down Company Picnic"},{"appid":639127,"name":"Party Down: Joel Munt's Big Deal Party"},{"appid":639128,"name":"Party Down: Cole Landry's Draft Day Party"},{"appid":639129,"name":"Party Down: Constance Carmell Wedding"},{"appid":639130,"name":"Ultrawings"},{"appid":639150,"name":"Timore 5: The Flood"},{"appid":639170,"name":"Minecraft: Story Mode - Season Two"},{"appid":639180,"name":"Time, Space and Matter"},{"appid":639190,"name":"SANKHARA"},{"appid":639200,"name":"Shadow Over Isolation Demo"},{"appid":639210,"name":"OVIVO Demo"},{"appid":639220,"name":"Throttle Powah VR"},{"appid":639230,"name":"Rival Books of Aster"},{"appid":639240,"name":"CodeRed: Agent Sarah's Story - Day One"},{"appid":639250,"name":"Rival Books of Aster - Heptameron Starter Deck"},{"appid":639260,"name":"Rival Books of Aster - Theurgia Goetia Starter Deck"},{"appid":639261,"name":"Rival Books of Aster - Grimoirum Verum Starter Deck"},{"appid":639262,"name":"Rival Books of Aster - Pauline Art Starter Deck"},{"appid":639263,"name":"Rival Books of Aster - Heptameron Expansion Pack"},{"appid":639264,"name":"Rival Books of Aster - Theurgia Goetia Expansion Pack"},{"appid":639265,"name":"Rival Books of Aster - Grimoirum Verum Expansion Pack"},{"appid":639266,"name":"Rival Books of Aster - Pauline Art Expansion Pack"},{"appid":639270,"name":"Operation Warcade VR"},{"appid":639280,"name":"Lander 8009 VR"},{"appid":639300,"name":"Age of Gladiators II: Death League"},{"appid":639310,"name":"Shantae: Pirate Queen's Quest"},{"appid":639320,"name":"Fading"},{"appid":639330,"name":"Naruto Spin-Off: Rock Lee & His Ninja Pals: Rock Lee Is a Ninja Who Can't Use Ninjutsu/Rock Lee's Rival Is Naruto"},{"appid":639331,"name":"Naruto Spin-Off: Rock Lee & His Ninja Pals: Love Is a Part of the Springtime of Youth/Love Makes Both Sides Crazy"},{"appid":639332,"name":"Naruto Spin-Off: Rock Lee & His Ninja Pals: A Competition With the Genius Ninja, Neji/Tenten's Must-Win Battle"},{"appid":639333,"name":"Naruto Spin-Off: Rock Lee & His Ninja Pals: Guy Sensei Didn't...Do It... / Guy Sensei's Rival Is Kakashi Sensei"},{"appid":639334,"name":"Naruto Spin-Off: Rock Lee & His Ninja Pals: I'm Going to Teach Konohamaru Kempo/ I Save My Lucky Undies for Physicals"},{"appid":639335,"name":"Naruto Spin-Off: Rock Lee & His Ninja Pals: The Leaf Village Sports Meet/ Calvary Battles Are Part of the Thrill of Youth"},{"appid":639336,"name":"Naruto Spin-Off: Rock Lee & His Ninja Pals: Orochimaru Is a B-Type Scorpio/ Love Letters Are the Ultimate Trap"},{"appid":639337,"name":"Naruto Spin-Off: Rock Lee & His Ninja Pals: Even Hokage Wear Out / Orochimaru Is Persistent"},{"appid":638860,"name":"Bokida - Heartfelt Reunion Soundtrack"},{"appid":638890,"name":"VEGA Conflict - Punisher Pack"},{"appid":638891,"name":"VEGA Conflict - Dominion Pack"},{"appid":638900,"name":"Defenders of the Realm VR"},{"appid":638920,"name":"BeanVR"},{"appid":638930,"name":"Dal Segno"},{"appid":638950,"name":"Eternal Destiny - The Attribute Sanctuaries"},{"appid":638970,"name":"Yakuza 0"},{"appid":638980,"name":"Chess Ultra Academy game pack"},{"appid":638981,"name":"Chess Ultra Isle of Lewis chess set"},{"appid":638990,"name":"UNDYING"},{"appid":639000,"name":"Chess Ultra Easter Island chess set"},{"appid":639001,"name":"Chess Ultra Imperial chess set"},{"appid":639030,"name":"Unexplored Ripley Run"},{"appid":639050,"name":"Battle Islands: Commanders - Exclusive E3 Crate"},{"appid":639070,"name":"Dropzone - Pilot Pack"},{"appid":639080,"name":"Polygon Attack OST"},{"appid":639090,"name":"The Girlfriend Experience: Entry"},{"appid":639091,"name":"The Girlfriend Experience: A Friend"},{"appid":639092,"name":"The Girlfriend Experience: Retention"},{"appid":639093,"name":"The Girlfriend Experience: Crossing The Line"},{"appid":639094,"name":"The Girlfriend Experience: Insurance"},{"appid":639095,"name":"The Girlfriend Experience: Boundaries"},{"appid":639096,"name":"The Girlfriend Experience: Access"},{"appid":639097,"name":"The Girlfriend Experience: Provocation"}]}