{"current":[{"appid":634595,"name":"The Royals: The Slings and Arrows of Outrageous Fortune"},{"appid":634596,"name":"The Royals: Your Sovereignty of Reason"},{"appid":634597,"name":"The Royals: The Great Man Down"},{"appid":634598,"name":"The Royals: In My Heart There was a Kind of Fighting"},{"appid":634599,"name":"The Royals: Our Wills and Fates do so Contrary Run"},{"appid":634610,"name":"The Royals: It Is Not, nor It Cannot Come to Good"},{"appid":634611,"name":"The Royals: Welcome is Fashion and Ceremony"},{"appid":634612,"name":"The Royals: Is Not This Something More Than Fantasy"},{"appid":634613,"name":"The Royals: What, Has This Thing Appear'd Again Tonight?"},{"appid":634614,"name":"The Royals: The Spirit That I Have Seen"},{"appid":634615,"name":"The Royals: Doubt Truth To Be A Liar"},{"appid":634616,"name":"The Royals: Taint Not Thy Mind, Nor Let Thy Soul Contrive Against Thy Mother"},{"appid":634617,"name":"The Royals: Be All My Sins Remembered"},{"appid":634618,"name":"The Royals: And Then It Started Like a Guilty Thing"},{"appid":634620,"name":"Nurse Jackie: Pilot"},{"appid":634621,"name":"Nurse Jackie: Sweet 'N All"},{"appid":634622,"name":"Nurse Jackie: Chicken Soup"},{"appid":634410,"name":"A Story Beside"},{"appid":634420,"name":"Suncore Chronicles: The Tower - Level 1"},{"appid":634421,"name":"Suncore Chronicles: The Tower - Level 2"},{"appid":634150,"name":"ReSizE"},{"appid":634160,"name":"Cattails"},{"appid":634170,"name":"Empathy: Path of Whispers - Original soundtrack"},{"appid":634180,"name":"Darkarta: A Broken Heart's Quest Standard Edition"},{"appid":634190,"name":"Spartacus: Past Transgressions"},{"appid":634191,"name":"Spartacus: Missio"},{"appid":634193,"name":"Spartacus: Paterfamilias"},{"appid":634194,"name":"Spartacus: Beneath the Mask"},{"appid":634195,"name":"Spartacus: Reckoning"},{"appid":634196,"name":"Spartacus: The Bitter End"},{"appid":634200,"name":"Tanks vs Aliens"},{"appid":634230,"name":"Project First Contact"},{"appid":634250,"name":"Australiens"},{"appid":634260,"name":"Getting Schooled"},{"appid":634270,"name":"Excess Flesh"},{"appid":634280,"name":"Arachnicide"},{"appid":634300,"name":"Knucklebones"},{"appid":634310,"name":"Blood Punch"},{"appid":634320,"name":"Skeleton Key 3 Part 2"},{"appid":634330,"name":"My Bloody Banjo"},{"appid":634340,"name":"Legend of Himari"},{"appid":633804,"name":"Spartacus: Decimation"},{"appid":633805,"name":"Spartacus: Blood Brothers"},{"appid":633806,"name":"Spartacus: Spoils of War"},{"appid":633807,"name":"Spartacus: Mors Indecepta"},{"appid":633808,"name":"Spartacus: Separate Paths"},{"appid":633809,"name":"Spartacus: The Dead and the Dying"},{"appid":633811,"name":"Spartacus: Victory"},{"appid":633830,"name":"Mega Overload VR Demo"},{"appid":633860,"name":"Spartacus: Wrath of the Gods"},{"appid":633870,"name":"Spartacus: Revelations"},{"appid":633871,"name":"Spartacus: Kill Them All"},{"appid":633910,"name":"Zombie Panic! Source Official Soundtrack"},{"appid":633930,"name":"Yeah Jam Fury: U, Me, Everybody!"},{"appid":633940,"name":"VisionOriginVR"},{"appid":633950,"name":"Fall of Light: Darkest Edition"},{"appid":633960,"name":"Two Worlds II - Soundtrack"},{"appid":633961,"name":"Two Worlds II - PotFF Soundtrack"},{"appid":633963,"name":"Two Worlds II - Digital Deluxe Content"},{"appid":633970,"name":"Heroes Never Die"},{"appid":633980,"name":"Two Worlds II - CoT Soundtrack"},{"appid":633981,"name":"Two Worlds II - SE Soundtrack"},{"appid":634010,"name":"Awesomenauts - Kunoichi Dizzy Skin"},{"appid":634012,"name":"Awesomenauts - Commander Cook-It Skin"},{"appid":634014,"name":"Awesomenauts - Dark Masquerade Qi'Tara Skin"},{"appid":634016,"name":"Awesomenauts - Bozo Gunk Skin"},{"appid":634030,"name":"Monster Slayers - Fire & Steel Expansion"},{"appid":634040,"name":"Caveman Warriors - Soundtrack"},{"appid":634060,"name":"ObserVRtarium"},{"appid":634070,"name":"Murnatan"},{"appid":634090,"name":"Suncore Chronicles: The Tower"},{"appid":634120,"name":"Inmates"},{"appid":633690,"name":"K - The Complete Series: Kindness"},{"appid":633691,"name":"K - The Complete Series: Kismet"},{"appid":633693,"name":"K - The Complete Series: Ken"},{"appid":633694,"name":"K - The Complete Series: Keeper"},{"appid":633695,"name":"K - The Complete Series: Kickdown"},{"appid":633696,"name":"K - The Complete Series: Kaput"},{"appid":633697,"name":"K - The Complete Series: Kid's Room"},{"appid":633698,"name":"K - The Complete Series: Keystone"},{"appid":633699,"name":"K - The Complete Series: Kali-yuga"},{"appid":633700,"name":"K - The Complete Series: Knuckle Bump"},{"appid":633701,"name":"K - The Complete Series: Knot"},{"appid":633710,"name":"K - The Complete Series: Kings"},{"appid":633730,"name":"The White Queen: In Love With the King"},{"appid":633731,"name":"The White Queen: The Price of Power"},{"appid":633732,"name":"The White Queen: The Storm"},{"appid":633733,"name":"The White Queen: The Bad Queen"},{"appid":633734,"name":"The White Queen: War at First Hand"},{"appid":633735,"name":"The White Queen: Love and Death"},{"appid":633736,"name":"The White Queen: Poison and Malmsey"},{"appid":633737,"name":"The White Queen: Long Live the King"},{"appid":633738,"name":"The White Queen: The Princes in the Tower"},{"appid":633739,"name":"The White Queen: The Final Battle"},{"appid":633770,"name":"Spartacus: The Red Serpent"},{"appid":633771,"name":"Spartacus: Sacramentum Gladiatorum"},{"appid":633772,"name":"Spartacus: Legends"},{"appid":633773,"name":"Spartacus: The Thing in the Pit"},{"appid":633774,"name":"Spartacus: Shadow Games"},{"appid":633776,"name":"Spartacus: Delicate Things"}]}